adtools/__init__.py
adtools/cli.py
adtools/py_code.py
adtools/ad_agent/__init__.py
adtools/ad_agent/ad_agent_utils.py
adtools/ad_agent/protocol.py
adtools/ad_agent/methods/__init__.py
adtools/ad_agent/methods/funsearch/__init__.py
adtools/ad_agent/third_party/__init__.py
adtools/ad_agent/third_party/algobleu/__init__.py
adtools/ad_agent/utils/__init__.py
adtools/ad_agent/utils/logger.py
adtools/evaluator/__init__.py
adtools/evaluator/auto_server.py
adtools/evaluator/py_evaluator.py
adtools/evaluator/py_evaluator_ray.py
adtools/lm/__init__.py
adtools/lm/lm_base.py
adtools/lm/openai_api.py
adtools/lm/sglang_server.py
adtools/lm/vllm_server.py
adtools/sandbox/__init__.py
adtools/sandbox/decorators.py
adtools/sandbox/sandbox_executor.py
adtools/sandbox/sandbox_executor_ray.py
adtools/sandbox/utils.py
py_adtools-0.3.7.dist-info/licenses/LICENSE
py_adtools-0.3.7.dist-info/METADATA
py_adtools-0.3.7.dist-info/WHEEL
py_adtools-0.3.7.dist-info/entry_points.txt
py_adtools-0.3.7.dist-info/top_level.txt
py_adtools-0.3.7.dist-info/RECORD
