Metadata-Version: 2.4
Name: py-adtools
Version: 0.3.7
Summary: Useful tools for parsing and evaluating Python programs for LLM-based algorithm design.
Author-email: Rui Zhang <rzhang.cs@gmail.com>
License-Expression: MIT
Project-URL: Homepage, https://github.com/RayZhhh/py-adtools
Classifier: Programming Language :: Python :: 3
Classifier: Operating System :: OS Independent
Classifier: Intended Audience :: Developers
Classifier: Topic :: Scientific/Engineering
Requires-Python: >=3.10
License-File: LICENSE
Requires-Dist: psutil
Requires-Dist: openai
Requires-Dist: ray<2.49.0,>=2.48.0
Requires-Dist: requests
Dynamic: license-file
